MANIFEST.in
setup.py
apiset/__init__.py
apiset/version.py
apiset.egg-info/PKG-INFO
apiset.egg-info/SOURCES.txt
apiset.egg-info/dependency_links.txt
apiset.egg-info/requires.txt
apiset.egg-info/top_level.txt
apiset/static/swagger-ui/favicon-16x16.png
apiset/static/swagger-ui/favicon-32x32.png
apiset/static/swagger-ui/index.html
apiset/static/swagger-ui/oauth2-redirect.html
apiset/static/swagger-ui/swagger-ui-bundle.js
apiset/static/swagger-ui/swagger-ui-bundle.js.map
apiset/static/swagger-ui/swagger-ui-standalone-preset.js
apiset/static/swagger-ui/swagger-ui-standalone-preset.js.map
apiset/static/swagger-ui/swagger-ui.css
apiset/static/swagger-ui/swagger-ui.css.map
apiset/static/swagger-ui/swagger-ui.js
apiset/static/swagger-ui/swagger-ui.js.map
apiset/templates/swagger-ui/index.html